{
  "bank_id": "otp_rs",
  "brand_name": "OTP Banka",
  "official_name": "OTP banka Srbija a.d. Novi Sad",
  "maticni_broj": "08049587",
  "website": "https://www.otpbanka.rs",
  "logo_color": "#00803C",
  "last_updated": "2026-05-30",
  "kyc_matrix": [
    {
      "status": "non_resident",
      "legal_type": "individual",
      "is_available": true,
      "probability": "medium",
      "required_docs": [
        "Загранпаспорт",
        "Белый картон"
      ],
      "red_flags": [
        "Политика меняется по отделениям. В Белграде лояльнее, в малых городах — частые отказы."
      ],
      "blocked_reasons": []
    },
    {
      "status": "resident_less_1y",
      "legal_type": "individual",
      "is_available": true,
      "probability": "high",
      "required_docs": [
        "Загранпаспорт",
        "ID-карта ВНЖ"
      ],
      "red_flags": [],
      "blocked_reasons": []
    },
    {
      "status": "resident_more_1y",
      "legal_type": "individual",
      "is_available": true,
      "probability": "high",
      "required_docs": [
        "Загранпаспорт",
        "ID-карта ВНЖ"
      ],
      "red_flags": [],
      "blocked_reasons": []
    },
    {
      "status": "permanent_resident",
      "legal_type": "individual",
      "is_available": true,
      "probability": "high",
      "required_docs": [
        "ID-карта ПМЖ"
      ],
      "red_flags": [],
      "blocked_reasons": []
    },
    {
      "status": "citizen",
      "legal_type": "individual",
      "is_available": true,
      "probability": "high",
      "required_docs": [
        "Лична карта (ID)"
      ],
      "red_flags": [],
      "blocked_reasons": []
    },
    {
      "status": "non_resident",
      "legal_type": "business",
      "is_available": false,
      "probability": "blocked",
      "required_docs": [],
      "red_flags": [
        "Бизнес-счета без ВНЖ не открывают."
      ],
      "blocked_reasons": [
        "Zakon o deviznom poslovanju: для открытия бизнес-счёта иностранцем обязательна регистрация в APR, которая требует боравак",
        "НБС-правило: банк обязан идентифицировать налоговый адрес предпринимателя — невозможно без подтверждённого ВНЖ"
      ]
    },
    {
      "status": "resident_less_1y",
      "legal_type": "business",
      "is_available": true,
      "probability": "medium",
      "required_docs": [
        "Загранпаспорт",
        "ID ВНЖ",
        "Решение APR",
        "PIB"
      ],
      "red_flags": [
        "Могут запросить дополнительные документы: первый инвойс от клиента или contract summary."
      ],
      "blocked_reasons": []
    },
    {
      "status": "resident_more_1y",
      "legal_type": "business",
      "is_available": true,
      "probability": "high",
      "required_docs": [
        "ID ВНЖ",
        "Решение APR",
        "PIB"
      ],
      "red_flags": [],
      "blocked_reasons": []
    },
    {
      "status": "permanent_resident",
      "legal_type": "business",
      "is_available": true,
      "probability": "high",
      "required_docs": [
        "ID ПМЖ",
        "Решение APR"
      ],
      "red_flags": [],
      "blocked_reasons": []
    },
    {
      "status": "citizen",
      "legal_type": "business",
      "is_available": true,
      "probability": "high",
      "required_docs": [
        "Лична карта",
        "Решение APR"
      ],
      "red_flags": [],
      "blocked_reasons": []
    }
  ],
  "products": [
    {
      "product_id": "otp_personal_standard",
      "name": "Tekući račun Standard",
      "category": "personal_account",
      "is_multicurrency": true,
      "supported_currencies": [
        "RSD",
        "EUR",
        "USD"
      ],
      "maintenance_fee_rsd": 250,
      "swift_in": {
        "pct": 1.0,
        "min_rsd": 800,
        "max_rsd": null,
        "notes": "Одна из самых высоких входящих комиссий среди системных банков."
      },
      "swift_out": {
        "pct": 1.0,
        "min_rsd": 1500,
        "max_rsd": null,
        "notes": "Исходящий SWIFT нерезидентам — только в кассе (онлайн недоступен)."
      },
      "features": {
        "apple_pay": false,
        "google_pay": true,
        "garmin_pay": false,
        "prenesi": true,
        "ips_qr": true,
        "contactless": true
      },
      "cards": {
        "dina_notes": "Выпускается обязательно для RSD-счёта.",
        "international": [
          "Visa Classic",
          "Mastercard Standard"
        ]
      },
      "card_issue_days": "До 5 рабочих дней",
      "cashback": "До 3% в категории «Супермаркеты» при обороте от 15 000 RSD/мес",
      "bonuses": "Программа OTP Moja Nagrada — баллы за покупки, обмен на скидки у партнёров"
    },
    {
      "product_id": "otp_business_account",
      "name": "Poslovni račun (ИП)",
      "category": "business_account",
      "is_multicurrency": true,
      "supported_currencies": [
        "RSD",
        "EUR"
      ],
      "maintenance_fee_rsd": 600,
      "swift_in": {
        "pct": 0.8,
        "min_rsd": 1000,
        "max_rsd": null,
        "notes": null
      },
      "swift_out": {
        "pct": 0.8,
        "min_rsd": 2000,
        "max_rsd": null,
        "notes": null
      },
      "features": {
        "apple_pay": false,
        "google_pay": true,
        "garmin_pay": false,
        "prenesi": false,
        "ips_qr": true,
        "contactless": true
      },
      "cards": {
        "dina_notes": "DinaCard Business для внутренних расчётов.",
        "international": [
          "Visa Business"
        ]
      },
      "card_issue_days": "До 7 рабочих дней",
      "cashback": "Нет",
      "bonuses": "OTP Business Center — онлайн-бухгалтерия и ВЭД-отчётность"
    },
    {
      "product_id": "otp_stednja_rsd",
      "name": "Oročena štednja RSD",
      "category": "savings_deposit",
      "currencies": [
        "RSD"
      ],
      "terms": [
        {
          "term_months": 6,
          "rate_pct": 6.0,
          "early_withdrawal_penalty_pct": 50
        },
        {
          "term_months": 12,
          "rate_pct": 7.5,
          "early_withdrawal_penalty_pct": 100
        },
        {
          "term_months": 24,
          "rate_pct": 8.0,
          "early_withdrawal_penalty_pct": 100
        }
      ],
      "tax_on_interest_pct": 0,
      "tax_note": "RSD-вклады — 0% налог.",
      "min_amount_rsd": 5000,
      "is_available_non_resident": true,
      "notes": "Можно открыть при наличии RSD-счёта. Капитализация процентов — по окончании срока."
    },
    {
      "product_id": "otp_stednja_eur",
      "name": "Oročena štednja EUR",
      "category": "savings_deposit",
      "currencies": [
        "EUR"
      ],
      "terms": [
        {
          "term_months": 3,
          "rate_pct": 1.8,
          "early_withdrawal_penalty_pct": 50
        },
        {
          "term_months": 12,
          "rate_pct": 3.0,
          "early_withdrawal_penalty_pct": 100
        },
        {
          "term_months": 24,
          "rate_pct": 3.3,
          "early_withdrawal_penalty_pct": 100
        }
      ],
      "tax_on_interest_pct": 15,
      "tax_note": "15% налог на процентный доход. Банк — налоговый агент.",
      "min_amount_eur": 100,
      "is_available_non_resident": false,
      "notes": null
    },
    {
      "product_id": "otp_bonds_gov",
      "name": "Državne obveznice (Гособлигации)",
      "category": "investment_bonds",
      "access_method": "offline_branch",
      "available_via_bank": true,
      "min_residency_status": "non_resident",
      "instrument_type": "RS_GOV",
      "currencies_available": [
        "EUR",
        "RSD"
      ],
      "yield_eur_approx_pct": 4.0,
      "yield_rsd_approx_pct": 6.8,
      "tax_on_coupon_pct": 0,
      "tax_on_capital_gains_pct": 0,
      "tax_note": "0% по купонам и приросту капитала для физлиц.",
      "entry_fee_pct": 5.0,
      "custody_fee_pct_annual": 1.0,
      "coupon_collection_fee_pct": 0.5,
      "min_investment_eur": 1000,
      "access_note": "OTP — один из немногих банков, открывающих брокерский счёт нерезидентам для покупки гособлигаций.",
      "red_flags": [
        "Комиссия за вход 5% — самая высокая в списке. Инвестиция окупается только на горизонте 3+ лет.",
        "Все операции только офлайн, очереди возможны."
      ],
      "notes": "Плюс: открыт для нерезидентов. Минус: дорогой вход."
    },
    {
      "product_id": "otp_mortgage",
      "name": "Stambeni kredit (Ипотека)",
      "category": "credit_mortgage",
      "min_residency_status": "resident_more_1y",
      "available_for_foreigners": true,
      "currency": "EUR",
      "rate_type": "variable",
      "rate_base": "EURIBOR 3M",
      "rate_margin_pct": 3.1,
      "rate_approx_total_pct": 6.0,
      "loan_term_years": [
        10,
        15,
        20,
        25
      ],
      "max_ltv_pct": 70,
      "min_down_payment_pct": 30,
      "min_amount_eur": 20000,
      "max_amount_eur": 400000,
      "income_requirement": "Сербский доход от 12 мес, без задолженностей в кредитном бюро",
      "required_docs": [
        "ID ВНЖ",
        "Выписки со счёта за 6 месяцев",
        "Налоговая декларация",
        "Оценка объекта"
      ],
      "red_flags": [
        "Ставка выше средней по рынку.",
        "Обязательна страховка жизни заёмщика."
      ],
      "notes": null
    },
    {
      "product_id": "otp_transfer_swift",
      "name": "Международный перевод SWIFT",
      "category": "transfer",
      "available_directions": [
        "incoming",
        "outgoing"
      ],
      "outgoing_resident_restriction": "Нерезиденты — только в кассе с предъявлением основания платежа",
      "outgoing_resident_1y_plus": "Через интернет-банк с суммами до 10 000 EUR без документов",
      "fee_incoming_pct": 1.0,
      "fee_incoming_min_rsd": 800,
      "fee_outgoing_pct": 1.0,
      "fee_outgoing_min_rsd": 1500,
      "fee_outgoing_max_rsd": null,
      "supported_currencies": [
        "EUR",
        "USD",
        "CHF"
      ],
      "notes": "Самые высокие SWIFT-комиссии среди топ-5 банков. Рекомендуется только если уже есть счёт для облигаций."
    }
  ]
}